{
    "swagger": "2.0",
    "info": {
        "description": "Hệ thống quản lý và giám sát nông nghiệp thông minh qua IoT.",
        "title": "Smart Agriculture API",
        "contact": {
            "name": "API Support",
            "email": "support@example.com"
        },
        "license": {
            "name": "Apache 2.0",
            "url": "http://www.apache.org/licenses/LICENSE-2.0.html"
        },
        "version": "1.0"
    },
    "host": "localhost:8080",
    "basePath": "/",
    "paths": {
        "/IOT-api/device/sensor-data": {
            "post": {
                "security": [
                    {
                        "ApiKeyAuth": []
                    }
                ],
                "description": "Thiết bị gửi dữ liệu cảm biến (mưa, ánh sáng, độ ẩm, PH) về hệ thống",
                "consumes": [
                    "application/json"
                ],
                "produces": [
                    "application/json"
                ],
                "tags": [
                    "Sensors"
                ],
                "summary": "Lưu dữ liệu cảm biến",
                "parameters": [
                    {
                        "description": "Dữ liệu sensor",
                        "name": "request",
                        "in": "body",
                        "required": true,
                        "schema": {
                            "$ref": "#/definitions/dto.CreateSensorDataRequest"
                        }
                    }
                ],
                "responses": {
                    "201": {
                        "description": "Created",
                        "schema": {
                            "$ref": "#/definitions/response.Response"
                        }
                    },
                    "400": {
                        "description": "Bad Request",
                        "schema": {
                            "$ref": "#/definitions/response.Response"
                        }
                    },
                    "401": {
                        "description": "Unauthorized",
                        "schema": {
                            "$ref": "#/definitions/response.Response"
                        }
                    },
                    "500": {
                        "description": "Internal Server Error",
                        "schema": {
                            "$ref": "#/definitions/response.Response"
                        }
                    }
                }
            }
        },
        "/IOT-api/device/{deviceID}/sensor-data": {
            "get": {
                "security": [
                    {
                        "BearerAuth": []
                    }
                ],
                "description": "Người dùng lấy các bản ghi dữ liệu gần nhất của một thiết bị",
                "consumes": [
                    "application/json"
                ],
                "produces": [
                    "application/json"
                ],
                "tags": [
                    "Sensors"
                ],
                "summary": "Lấy lịch sử dữ liệu cảm biến",
                "parameters": [
                    {
                        "type": "string",
                        "description": "ID của thiết bị (UUID)",
                        "name": "deviceID",
                        "in": "path",
                        "required": true
                    },
                    {
                        "type": "integer",
                        "description": "Số lượng bản ghi muốn lấy (mặc định 1)",
                        "name": "number",
                        "in": "query"
                    }
                ],
                "responses": {
                    "200": {
                        "description": "OK",
                        "schema": {
                            "allOf": [
                                {
                                    "$ref": "#/definitions/response.Response"
                                },
                                {
                                    "type": "object",
                                    "properties": {
                                        "data": {
                                            "type": "array",
                                            "items": {
                                                "$ref": "#/definitions/dto.SensorDataResponse"
                                            }
                                        }
                                    }
                                }
                            ]
                        }
                    },
                    "400": {
                        "description": "Bad Request",
                        "schema": {
                            "$ref": "#/definitions/response.Response"
                        }
                    },
                    "401": {
                        "description": "Unauthorized",
                        "schema": {
                            "$ref": "#/definitions/response.Response"
                        }
                    },
                    "500": {
                        "description": "Internal Server Error",
                        "schema": {
                            "$ref": "#/definitions/response.Response"
                        }
                    }
                }
            }
        },
        "/IOT-api/web/devices": {
            "get": {
                "security": [
                    {
                        "BearerAuth": []
                    }
                ],
                "description": "Lấy danh sách tất cả thiết bị của người dùng hiện tại",
                "consumes": [
                    "application/json"
                ],
                "produces": [
                    "application/json"
                ],
                "tags": [
                    "Devices"
                ],
                "summary": "Danh sách thiết bị",
                "responses": {
                    "200": {
                        "description": "OK",
                        "schema": {
                            "allOf": [
                                {
                                    "$ref": "#/definitions/response.Response"
                                },
                                {
                                    "type": "object",
                                    "properties": {
                                        "data": {
                                            "type": "array",
                                            "items": {
                                                "$ref": "#/definitions/dto.DeviceResponse"
                                            }
                                        }
                                    }
                                }
                            ]
                        }
                    },
                    "500": {
                        "description": "Internal Server Error",
                        "schema": {
                            "$ref": "#/definitions/response.Response"
                        }
                    }
                }
            },
            "post": {
                "security": [
                    {
                        "BearerAuth": []
                    }
                ],
                "description": "Người dùng thêm thiết bị (cảm biến) mới vào hệ thống",
                "consumes": [
                    "application/json"
                ],
                "produces": [
                    "application/json"
                ],
                "tags": [
                    "Devices"
                ],
                "summary": "Thêm thiết bị mới",
                "parameters": [
                    {
                        "description": "Thông tin thiết bị mới",
                        "name": "request",
                        "in": "body",
                        "required": true,
                        "schema": {
                            "$ref": "#/definitions/dto.CreateDeviceRequest"
                        }
                    }
                ],
                "responses": {
                    "201": {
                        "description": "Created",
                        "schema": {
                            "$ref": "#/definitions/response.Response"
                        }
                    },
                    "400": {
                        "description": "Bad Request",
                        "schema": {
                            "$ref": "#/definitions/response.Response"
                        }
                    },
                    "500": {
                        "description": "Internal Server Error",
                        "schema": {
                            "$ref": "#/definitions/response.Response"
                        }
                    }
                }
            }
        },
        "/IOT-api/web/devices/{deviceID}": {
            "get": {
                "security": [
                    {
                        "BearerAuth": []
                    }
                ],
                "description": "Lấy thông tin chi tiết của một thiết bị theo ID",
                "consumes": [
                    "application/json"
                ],
                "produces": [
                    "application/json"
                ],
                "tags": [
                    "Devices"
                ],
                "summary": "Chi tiết thiết bị",
                "parameters": [
                    {
                        "type": "string",
                        "description": "ID của thiết bị (UUID)",
                        "name": "deviceID",
                        "in": "path",
                        "required": true
                    }
                ],
                "responses": {
                    "200": {
                        "description": "OK",
                        "schema": {
                            "allOf": [
                                {
                                    "$ref": "#/definitions/response.Response"
                                },
                                {
                                    "type": "object",
                                    "properties": {
                                        "data": {
                                            "$ref": "#/definitions/dto.DeviceResponse"
                                        }
                                    }
                                }
                            ]
                        }
                    },
                    "400": {
                        "description": "Bad Request",
                        "schema": {
                            "$ref": "#/definitions/response.Response"
                        }
                    },
                    "404": {
                        "description": "Not Found",
                        "schema": {
                            "$ref": "#/definitions/response.Response"
                        }
                    },
                    "500": {
                        "description": "Internal Server Error",
                        "schema": {
                            "$ref": "#/definitions/response.Response"
                        }
                    }
                }
            },
            "delete": {
                "security": [
                    {
                        "BearerAuth": []
                    }
                ],
                "description": "Xóa một thiết bị khỏi hệ thống",
                "consumes": [
                    "application/json"
                ],
                "produces": [
                    "application/json"
                ],
                "tags": [
                    "Devices"
                ],
                "summary": "Xóa thiết bị",
                "parameters": [
                    {
                        "type": "string",
                        "description": "ID của thiết bị (UUID)",
                        "name": "deviceID",
                        "in": "path",
                        "required": true
                    }
                ],
                "responses": {
                    "200": {
                        "description": "OK",
                        "schema": {
                            "$ref": "#/definitions/response.Response"
                        }
                    },
                    "400": {
                        "description": "Bad Request",
                        "schema": {
                            "$ref": "#/definitions/response.Response"
                        }
                    },
                    "500": {
                        "description": "Internal Server Error",
                        "schema": {
                            "$ref": "#/definitions/response.Response"
                        }
                    }
                }
            },
            "patch": {
                "security": [
                    {
                        "BearerAuth": []
                    }
                ],
                "description": "Cập nhật thông tin của một thiết bị (chỉ cập nhật các trường được gửi)",
                "consumes": [
                    "application/json"
                ],
                "produces": [
                    "application/json"
                ],
                "tags": [
                    "Devices"
                ],
                "summary": "Cập nhật thiết bị",
                "parameters": [
                    {
                        "type": "string",
                        "description": "ID của thiết bị (UUID)",
                        "name": "deviceID",
                        "in": "path",
                        "required": true
                    },
                    {
                        "description": "Thông tin cập nhật",
                        "name": "request",
                        "in": "body",
                        "required": true,
                        "schema": {
                            "$ref": "#/definitions/dto.UpdateDeviceRequest"
                        }
                    }
                ],
                "responses": {
                    "200": {
                        "description": "OK",
                        "schema": {
                            "$ref": "#/definitions/response.Response"
                        }
                    },
                    "400": {
                        "description": "Bad Request",
                        "schema": {
                            "$ref": "#/definitions/response.Response"
                        }
                    },
                    "500": {
                        "description": "Internal Server Error",
                        "schema": {
                            "$ref": "#/definitions/response.Response"
                        }
                    }
                }
            }
        },
        "/IOT-api/web/login": {
            "post": {
                "description": "Người dùng đăng nhập để lấy JWT Token",
                "consumes": [
                    "application/json"
                ],
                "produces": [
                    "application/json"
                ],
                "tags": [
                    "Auth"
                ],
                "summary": "Đăng nhập",
                "parameters": [
                    {
                        "description": "Thông tin đăng nhập",
                        "name": "request",
                        "in": "body",
                        "required": true,
                        "schema": {
                            "$ref": "#/definitions/dto.LoginRequest"
                        }
                    }
                ],
                "responses": {
                    "200": {
                        "description": "OK",
                        "schema": {
                            "allOf": [
                                {
                                    "$ref": "#/definitions/response.Response"
                                },
                                {
                                    "type": "object",
                                    "properties": {
                                        "data": {
                                            "$ref": "#/definitions/dto.LoginResponse"
                                        }
                                    }
                                }
                            ]
                        }
                    },
                    "400": {
                        "description": "Bad Request",
                        "schema": {
                            "$ref": "#/definitions/response.Response"
                        }
                    },
                    "401": {
                        "description": "Unauthorized",
                        "schema": {
                            "$ref": "#/definitions/response.Response"
                        }
                    },
                    "500": {
                        "description": "Internal Server Error",
                        "schema": {
                            "$ref": "#/definitions/response.Response"
                        }
                    }
                }
            }
        },
        "/IOT-api/web/register": {
            "post": {
                "description": "Người dùng đăng ký tài khoản mới bằng email và mật khẩu",
                "consumes": [
                    "application/json"
                ],
                "produces": [
                    "application/json"
                ],
                "tags": [
                    "Auth"
                ],
                "summary": "Đăng ký tài khoản",
                "parameters": [
                    {
                        "description": "Thông tin đăng ký",
                        "name": "request",
                        "in": "body",
                        "required": true,
                        "schema": {
                            "$ref": "#/definitions/dto.RegisterRequest"
                        }
                    }
                ],
                "responses": {
                    "201": {
                        "description": "Created",
                        "schema": {
                            "allOf": [
                                {
                                    "$ref": "#/definitions/response.Response"
                                },
                                {
                                    "type": "object",
                                    "properties": {
                                        "data": {
                                            "$ref": "#/definitions/dto.RegisterResponse"
                                        }
                                    }
                                }
                            ]
                        }
                    },
                    "400": {
                        "description": "Bad Request",
                        "schema": {
                            "$ref": "#/definitions/response.Response"
                        }
                    },
                    "500": {
                        "description": "Internal Server Error",
                        "schema": {
                            "$ref": "#/definitions/response.Response"
                        }
                    }
                }
            }
        }
    },
    "definitions": {
        "dto.CreateDeviceRequest": {
            "type": "object",
            "required": [
                "api_key",
                "device_name"
            ],
            "properties": {
                "api_key": {
                    "type": "string"
                },
                "device_name": {
                    "type": "string"
                },
                "location": {
                    "type": "string"
                }
            }
        },
        "dto.CreateSensorDataRequest": {
            "type": "object",
            "properties": {
                "light": {
                    "type": "number"
                },
                "ph": {
                    "type": "number"
                },
                "rain_level": {
                    "type": "number"
                },
                "soil_moisture": {
                    "type": "number"
                }
            }
        },
        "dto.DeviceResponse": {
            "type": "object",
            "properties": {
                "api_key": {
                    "type": "string"
                },
                "created_at": {
                    "type": "string"
                },
                "device_name": {
                    "type": "string"
                },
                "id": {
                    "type": "string"
                },
                "location": {
                    "type": "string"
                },
                "user_id": {
                    "type": "string"
                }
            }
        },
        "dto.LoginRequest": {
            "type": "object",
            "required": [
                "email",
                "password"
            ],
            "properties": {
                "email": {
                    "type": "string"
                },
                "password": {
                    "type": "string"
                }
            }
        },
        "dto.LoginResponse": {
            "type": "object",
            "properties": {
                "email": {
                    "type": "string"
                },
                "id": {
                    "type": "string"
                },
                "token": {
                    "type": "string"
                }
            }
        },
        "dto.RegisterRequest": {
            "type": "object",
            "required": [
                "email",
                "password"
            ],
            "properties": {
                "email": {
                    "type": "string"
                },
                "password": {
                    "type": "string"
                }
            }
        },
        "dto.RegisterResponse": {
            "type": "object",
            "properties": {
                "created_at": {
                    "type": "string"
                },
                "id": {
                    "type": "string"
                }
            }
        },
        "dto.SensorDataResponse": {
            "type": "object",
            "properties": {
                "created_at": {
                    "type": "string"
                },
                "light": {
                    "type": "number"
                },
                "ph": {
                    "type": "number"
                },
                "rain_level": {
                    "type": "number"
                },
                "soil_moisture": {
                    "type": "number"
                }
            }
        },
        "dto.UpdateDeviceRequest": {
            "type": "object",
            "properties": {
                "api_key": {
                    "type": "string"
                },
                "device_name": {
                    "type": "string"
                },
                "location": {
                    "type": "string"
                }
            }
        },
        "response.Response": {
            "type": "object",
            "properties": {
                "data": {},
                "error": {
                    "type": "string"
                },
                "message": {
                    "type": "string"
                },
                "success": {
                    "type": "boolean"
                }
            }
        }
    },
    "securityDefinitions": {
        "ApiKeyAuth": {
            "type": "apiKey",
            "name": "IOT-API-Key",
            "in": "header"
        },
        "BearerAuth": {
            "type": "apiKey",
            "name": "Authorization",
            "in": "header"
        }
    }
}